pytelecast/__init__.py
pytelecast/core.py
pytelecast/db_json.py
pytelecast/db_mongo.py
pytelecast/db_sqlite.py
pytelecast/utils.py
pytelecast-0.1.2.dist-info/licenses/LICENSE
pytelecast-0.1.2.dist-info/METADATA
pytelecast-0.1.2.dist-info/WHEEL
pytelecast-0.1.2.dist-info/top_level.txt
pytelecast-0.1.2.dist-info/RECORD
