Metadata-Version: 2.4
Name: pytelecast
Version: 0.1.2
Summary: A Telegram broadcast utility package with multiple database backends
Author-email: Manji Devs <ManjiStudios@outlook.com>
Classifier: Programming Language :: Python :: 3
Classifier: License :: OSI Approved :: MIT License
Classifier: Operating System :: OS Independent
Requires-Python: >=3.8
License-File: LICENSE
Requires-Dist: python-telegram-bot>=20.0
Requires-Dist: pymongo>=4.0
Dynamic: license-file
